{"title":"「足」夢踏實——自學方案參與心得","content":"#07期 文／吳云云、李千輝、林亮妤、黃素鳳　國立臺北大學學生 吳云云 (進修部經濟系同學) 「原本以為只有自己有這些困擾，但沒想到脫下鞋子後，大家都一樣嘛！」這句話我久久不能忘記，也讓我覺得，有機會可以辦這個活動真是太好了。  ...","hero_image":"https://static.wixstatic.com/media/044e32_84a6bc9b10224a61bd6a6f2c04496964~mv2.png/v1/fit/w_1000,h_1000,al_c,q_80/file.png","all_images":[],"creator":"","date":"April 22","year":2025,"link":"https://www.learningandaging.com/post/%E3%80%8C%E8%B6%B3%E3%80%8D%E5%A4%A2%E8%B8%8F%E5%AF%A6-%E8%87%AA%E5%AD%B8%E6%96%B9%E6%A1%88%E5%8F%83%E8%88%87%E5%BF%83%E5%BE%97","id":"67e0deb85a47b47069b122aa"}